varlens
