Metadata-Version: 1.1
Name: varlens
Version: 0.0.2
Summary: commandline manipulation of genomic variants and NGS reads
Home-page: https://github.com/hammerlab/varlens
Author: Tim O'Donnell
Author-email: timodonnell@gmail.com
License: http://www.apache.org/licenses/LICENSE-2.0.html
Platform: UNKNOWN
Classifier: Development Status :: 3 - Alpha
Classifier: Environment :: Console
Classifier: Operating System :: OS Independent
Classifier: Intended Audience :: Science/Research
Classifier: License :: OSI Approved :: Apache Software License
Classifier: Programming Language :: Python
Classifier: Topic :: Scientific/Engineering :: Bio-Informatics
